pypi_upload.sh
setup.cfg
setup.py
html2docbook/CHANGES.txt
html2docbook/LICENCE.txt
html2docbook/README.txt
html2docbook/__init__.py
html2docbook/html2docbook.xsl
html2docbook/version.txt
html2docbook.egg-info/PKG-INFO
html2docbook.egg-info/SOURCES.txt
html2docbook.egg-info/dependency_links.txt
html2docbook.egg-info/entry_points.txt
html2docbook.egg-info/not-zip-safe
html2docbook.egg-info/requires.txt
html2docbook.egg-info/top_level.txt
html2docbook/tests/__init__.py
html2docbook/tests/test_transformation.py