Metadata-Version: 1.0
Name: html2docbook
Version: 0.1
Summary: HTML to DocBook transformation
Home-page: UNKNOWN
Author: Timo Stollenwerk
Author-email: timo@zmag.de
License: GPL
Platform: UNKNOWN
